diff_diff/__init__.py
diff_diff/_backend.py
diff_diff/_rust_backend.cpython-312-x86_64-linux-gnu.so
diff_diff/bacon.py
diff_diff/diagnostics.py
diff_diff/estimators.py
diff_diff/honest_did.py
diff_diff/linalg.py
diff_diff/power.py
diff_diff/prep.py
diff_diff/pretrends.py
diff_diff/results.py
diff_diff/staggered.py
diff_diff/sun_abraham.py
diff_diff/synthetic_did.py
diff_diff/triple_diff.py
diff_diff/twfe.py
diff_diff/utils.py
diff_diff/visualization.py
diff_diff-2.0.2.dist-info/METADATA
diff_diff-2.0.2.dist-info/WHEEL
diff_diff.libs/libgfortran-83c28eba.so.5
diff_diff.libs/libopenblas-11edc3fa.so.0
diff_diff.libs/libquadmath-2284e583.so.0
diff_diff-2.0.2.dist-info/RECORD
