Metadata-Version: 2.4
Name: diff-diff
Version: 2.0.2
Classifier: Development Status :: 5 - Production/Stable
Classifier: Intended Audience :: Science/Research
Classifier: Operating System :: OS Independent
Classifier: Programming Language :: Python :: 3
Classifier: Programming Language :: Python :: 3.9
Classifier: Programming Language :: Python :: 3.10
Classifier: Programming Language :: Python :: 3.11
Classifier: Programming Language :: Python :: 3.12
Classifier: Topic :: Scientific/Engineering :: Mathematics
Requires-Dist: numpy>=1.20.0
Requires-Dist: pandas>=1.3.0
Requires-Dist: scipy>=1.7.0
Requires-Dist: pytest>=7.0 ; extra == 'dev'
Requires-Dist: pytest-cov>=4.0 ; extra == 'dev'
Requires-Dist: black>=23.0 ; extra == 'dev'
Requires-Dist: ruff>=0.1.0 ; extra == 'dev'
Requires-Dist: mypy>=1.0 ; extra == 'dev'
Requires-Dist: sphinx>=6.0 ; extra == 'docs'
Requires-Dist: sphinx-rtd-theme>=1.0 ; extra == 'docs'
Provides-Extra: dev
Provides-Extra: docs
Summary: A library for Difference-in-Differences causal inference analysis
Keywords: causal-inference,difference-in-differences,econometrics,statistics,treatment-effects
Author: diff-diff contributors
License-Expression: MIT
Requires-Python: >=3.9
Project-URL: Documentation, https://diff-diff.readthedocs.io
Project-URL: Homepage, https://github.com/igerber/diff-diff
Project-URL: Issues, https://github.com/igerber/diff-diff/issues
Project-URL: Repository, https://github.com/igerber/diff-diff
